{
    "name": "Controls",
    "maps": [
        {
            "name": "Ship Controls",
            "id": "c7a431b6-2816-45ad-a255-1b64f427a325",
            "actions": [
                {
                    "name": "Lateral Thrust",
                    "type": "Value",
                    "id": "96817b0b-d247-4fb3-9f6b-5ba370469614",
                    "expectedControlType": "Axis",
                    "processors": "",
                    "interactions": ""
                },
                {
                    "name": "Vertical Thrust",
                    "type": "Value",
                    "id": "d12e3020-636f-4bba-bd37-9fa233959fdb",
                    "expectedControlType": "Axis",
                    "processors": "",
                    "interactions": ""
                },
                {
                    "name": "Thrust",
                    "type": "Value",
                    "id": "ea823e61-9e30-40ff-bc42-5c6a5feed6b9",
                    "expectedControlType": "Axis",
                    "processors": "",
                    "interactions": ""
                },
                {
                    "name": "Pitch",
                    "type": "Value",
                    "id": "6cabece9-cb6a-45c7-a58b-228996769bfe",
                    "expectedControlType": "Axis",
                    "processors": "",
                    "interactions": ""
                },
                {
                    "name": "Yaw",
                    "type": "Value",
                    "id": "18bcdfcd-d18a-49f0-8b76-45669ed93805",
                    "expectedControlType": "Axis",
                    "processors": "",
                    "interactions": ""
                },
                {
                    "name": "Roll",
                    "type": "Value",
                    "id": "769d0e3e-d13d-4ed7-9bca-9850e0e93b89",
                    "expectedControlType": "Axis",
                    "processors": "",
                    "interactions": ""
                },
                {
                    "name": "Change Camera",
                    "type": "Button",
                    "id": "b0acd2a4-3a95-4a8a-a8ef-9a17ec5c1793",
                    "expectedControlType": "Button",
                    "processors": "",
                    "interactions": ""
                },
                {
                    "name": "Target",
                    "type": "Button",
                    "id": "7acc2dc5-de3b-4b25-b3d3-61ce00ce6d1a",
                    "expectedControlType": "Button",
                    "processors": "",
                    "interactions": ""
                },
                {
                    "name": "Decouple",
                    "type": "Button",
                    "id": "b654c8e6-1caa-4428-890c-0ea39612a0a2",
                    "expectedControlType": "Button",
                    "processors": "",
                    "interactions": ""
                },
                {
                    "name": "Vjoy",
                    "type": "Button",
                    "id": "5116f618-8f6b-44be-9e0a-71672e08b089",
                    "expectedControlType": "Button",
                    "processors": "",
                    "interactions": ""
                },
                {
                    "name": "Boost",
                    "type": "Button",
                    "id": "2126a231-609f-4147-8247-9635210ecf06",
                    "expectedControlType": "Button",
                    "processors": "",
                    "interactions": ""
                },
                {
                    "name": "Shoot",
                    "type": "Button",
                    "id": "f4e2e7e1-bbf6-4c0e-b8c4-c22c84dd505c",
                    "expectedControlType": "Button",
                    "processors": "",
                    "interactions": ""
                },
                {
                    "name": "Missile",
                    "type": "Button",
                    "id": "7d468f19-9df3-41f8-841f-e51d79b55f66",
                    "expectedControlType": "Button",
                    "processors": "",
                    "interactions": ""
                },
                {
                    "name": "Mouse Position",
                    "type": "Value",
                    "id": "67455a36-fa56-4b42-8a96-247f270bf26f",
                    "expectedControlType": "Vector2",
                    "processors": "",
                    "interactions": ""
                },
                {
                    "name": "Save Inputs",
                    "type": "Button",
                    "id": "866001ed-d58b-460b-8c49-4c0f4b24c0b0",
                    "expectedControlType": "Button",
                    "processors": "",
                    "interactions": ""
                }
            ],
            "bindings": [
                {
                    "name": "",
                    "id": "e3b2253f-bdca-4d55-8e41-c92d19bf4d59",
                    "path": "<Gamepad>/leftStick/x",
                    "interactions": "",
                    "processors": "",
                    "groups": "",
                    "action": "Lateral Thrust",
                    "isComposite": false,
                    "isPartOfComposite": false
                },
                {
                    "name": "AD",
                    "id": "ea400ffd-3988-45c5-be5c-2496ee0af771",
                    "path": "1DAxis",
                    "interactions": "",
                    "processors": "",
                    "groups": "",
                    "action": "Lateral Thrust",
                    "isComposite": true,
                    "isPartOfComposite": false
                },
                {
                    "name": "negative",
                    "id": "ccc8bce2-918a-431a-bceb-0973218c5961",
                    "path": "<Keyboard>/a",
                    "interactions": "",
                    "processors": "",
                    "groups": "",
                    "action": "Lateral Thrust",
                    "isComposite": false,
                    "isPartOfComposite": true
                },
                {
                    "name": "positive",
                    "id": "2a070d0a-bd7b-4f3b-914c-fd1c98c8614f",
                    "path": "<Keyboard>/d",
                    "interactions": "",
                    "processors": "",
                    "groups": "",
                    "action": "Lateral Thrust",
                    "isComposite": false,
                    "isPartOfComposite": true
                },
                {
                    "name": "",
                    "id": "d1ab53ec-8eea-4e86-8731-3efd3808acc3",
                    "path": "<Gamepad>/leftStick/y",
                    "interactions": "",
                    "processors": "",
                    "groups": "",
                    "action": "Vertical Thrust",
                    "isComposite": false,
                    "isPartOfComposite": false
                },
                {
                    "name": "SPACECTRL",
                    "id": "dc1e038a-789c-47b0-b6c1-12bb4f5da448",
                    "path": "1DAxis",
                    "interactions": "",
                    "processors": "",
                    "groups": "",
                    "action": "Vertical Thrust",
                    "isComposite": true,
                    "isPartOfComposite": false
                },
                {
                    "name": "negative",
                    "id": "bb53878d-6ab7-4361-9309-ed099b197d84",
                    "path": "<Keyboard>/ctrl",
                    "interactions": "",
                    "processors": "",
                    "groups": "",
                    "action": "Vertical Thrust",
                    "isComposite": false,
                    "isPartOfComposite": true
                },
                {
                    "name": "positive",
                    "id": "cfc6714f-1d18-487c-b648-26850beb42c6",
                    "path": "<Keyboard>/space",
                    "interactions": "",
                    "processors": "",
                    "groups": "",
                    "action": "Vertical Thrust",
                    "isComposite": false,
                    "isPartOfComposite": true
                },
                {
                    "name": "",
                    "id": "cc2700b0-e4d8-44a3-9d8d-1d282bd82470",
                    "path": "<Gamepad>/rightStick/y",
                    "interactions": "",
                    "processors": "",
                    "groups": "",
                    "action": "Pitch",
                    "isComposite": false,
                    "isPartOfComposite": false
                },
                {
                    "name": "",
                    "id": "28a131ee-64e2-457a-8708-98b1cc68fac3",
                    "path": "<Mouse>/delta/y",
                    "interactions": "",
                    "processors": "Scale(factor=0.1),Clamp(min=-1,max=1)",
                    "groups": "",
                    "action": "Pitch",
                    "isComposite": false,
                    "isPartOfComposite": false
                },
                {
                    "name": "",
                    "id": "0d1f13b1-dad0-43e4-a0ed-f2443107ecce",
                    "path": "<Gamepad>/rightStick/x",
                    "interactions": "",
                    "processors": "",
                    "groups": "",
                    "action": "Yaw",
                    "isComposite": false,
                    "isPartOfComposite": false
                },
                {
                    "name": "",
                    "id": "9010cde0-aced-43c0-b7a2-9d158d67c5bc",
                    "path": "<Mouse>/delta/x",
                    "interactions": "",
                    "processors": "Scale(factor=0.1),Clamp(min=-1,max=1)",
                    "groups": "",
                    "action": "Yaw",
                    "isComposite": false,
                    "isPartOfComposite": false
                },
                {
                    "name": "Shoulders",
                    "id": "4af531e8-d0e7-4601-9f3d-4a15490b3a7b",
                    "path": "1DAxis",
                    "interactions": "",
                    "processors": "",
                    "groups": "",
                    "action": "Roll",
                    "isComposite": true,
                    "isPartOfComposite": false
                },
                {
                    "name": "negative",
                    "id": "a0787f2b-4b32-4f8b-ae01-13bec8841964",
                    "path": "<Gamepad>/rightShoulder",
                    "interactions": "",
                    "processors": "",
                    "groups": "",
                    "action": "Roll",
                    "isComposite": false,
                    "isPartOfComposite": true
                },
                {
                    "name": "positive",
                    "id": "672c1c10-8fe5-449e-b7e2-f2fcf6002b3b",
                    "path": "<Gamepad>/leftShoulder",
                    "interactions": "",
                    "processors": "",
                    "groups": "",
                    "action": "Roll",
                    "isComposite": false,
                    "isPartOfComposite": true
                },
                {
                    "name": "QE",
                    "id": "0d9d264a-56f3-48f8-b830-f3b7acb7f4af",
                    "path": "1DAxis",
                    "interactions": "",
                    "processors": "",
                    "groups": "",
                    "action": "Roll",
                    "isComposite": true,
                    "isPartOfComposite": false
                },
                {
                    "name": "negative",
                    "id": "5504ef5d-0158-4f92-bc67-5e6e2a1545b3",
                    "path": "<Keyboard>/e",
                    "interactions": "",
                    "processors": "",
                    "groups": "",
                    "action": "Roll",
                    "isComposite": false,
                    "isPartOfComposite": true
                },
                {
                    "name": "positive",
                    "id": "b9b4d61c-b3e5-49c9-86e3-5ba7d7d09f9a",
                    "path": "<Keyboard>/q",
                    "interactions": "",
                    "processors": "",
                    "groups": "",
                    "action": "Roll",
                    "isComposite": false,
                    "isPartOfComposite": true
                },
                {
                    "name": "",
                    "id": "60a1a99d-37b0-459d-b6c2-8308b056801e",
                    "path": "<Keyboard>/c",
                    "interactions": "",
                    "processors": "",
                    "groups": "",
                    "action": "Change Camera",
                    "isComposite": false,
                    "isPartOfComposite": false
                },
                {
                    "name": "",
                    "id": "80626c71-5e0b-4978-a3e9-98aab18b217f",
                    "path": "<Gamepad>/leftStickPress",
                    "interactions": "",
                    "processors": "",
                    "groups": "",
                    "action": "Change Camera",
                    "isComposite": false,
                    "isPartOfComposite": false
                },
                {
                    "name": "",
                    "id": "e2642103-00d9-487e-80ab-559d774e13d8",
                    "path": "<Gamepad>/rightStickPress",
                    "interactions": "",
                    "processors": "",
                    "groups": "",
                    "action": "Target",
                    "isComposite": false,
                    "isPartOfComposite": false
                },
                {
                    "name": "",
                    "id": "12218368-4e84-4627-8fc1-8e640704f8b5",
                    "path": "<Mouse>/middleButton",
                    "interactions": "",
                    "processors": "",
                    "groups": "",
                    "action": "Target",
                    "isComposite": false,
                    "isPartOfComposite": false
                },
                {
                    "name": "",
                    "id": "4a464aff-609d-4594-85de-312575e746b7",
                    "path": "<Keyboard>/v",
                    "interactions": "",
                    "processors": "",
                    "groups": "",
                    "action": "Decouple",
                    "isComposite": false,
                    "isPartOfComposite": false
                },
                {
                    "name": "Triggers",
                    "id": "5e88abd5-aa13-4545-8e1f-b59b5e3a14cb",
                    "path": "1DAxis",
                    "interactions": "",
                    "processors": "",
                    "groups": "",
                    "action": "Thrust",
                    "isComposite": true,
                    "isPartOfComposite": false
                },
                {
                    "name": "negative",
                    "id": "d682653f-38a9-4d99-961f-dc1f4793b5e3",
                    "path": "<Gamepad>/leftTrigger",
                    "interactions": "",
                    "processors": "",
                    "groups": "",
                    "action": "Thrust",
                    "isComposite": false,
                    "isPartOfComposite": true
                },
                {
                    "name": "positive",
                    "id": "e6473cf8-d949-42d5-a879-7521e9ed33d2",
                    "path": "<Gamepad>/rightTrigger",
                    "interactions": "",
                    "processors": "",
                    "groups": "",
                    "action": "Thrust",
                    "isComposite": false,
                    "isPartOfComposite": true
                },
                {
                    "name": "WS",
                    "id": "b486dbb5-e2e4-49d2-a26d-8ba14411a7be",
                    "path": "1DAxis",
                    "interactions": "",
                    "processors": "",
                    "groups": "",
                    "action": "Thrust",
                    "isComposite": true,
                    "isPartOfComposite": false
                },
                {
                    "name": "negative",
                    "id": "162fdea4-6f7c-40fa-b707-9cb9d2f9055f",
                    "path": "<Keyboard>/s",
                    "interactions": "",
                    "processors": "",
                    "groups": "",
                    "action": "Thrust",
                    "isComposite": false,
                    "isPartOfComposite": true
                },
                {
                    "name": "positive",
                    "id": "49f7fcc2-a58e-418e-86ee-84a14d0a327a",
                    "path": "<Keyboard>/w",
                    "interactions": "",
                    "processors": "",
                    "groups": "",
                    "action": "Thrust",
                    "isComposite": false,
                    "isPartOfComposite": true
                },
                {
                    "name": "",
                    "id": "e8d9e18e-1302-40e5-8738-047926426b1e",
                    "path": "<Keyboard>/r",
                    "interactions": "",
                    "processors": "",
                    "groups": "",
                    "action": "Vjoy",
                    "isComposite": false,
                    "isPartOfComposite": false
                },
                {
                    "name": "",
                    "id": "5a07ca55-1d90-40ba-9519-a999186425d3",
                    "path": "<Mouse>/position",
                    "interactions": "",
                    "processors": "",
                    "groups": "",
                    "action": "Mouse Position",
                    "isComposite": false,
                    "isPartOfComposite": false
                },
                {
                    "name": "",
                    "id": "b018e0ae-2a3d-43b4-a5c8-ccfc9937f46d",
                    "path": "<Gamepad>/buttonSouth",
                    "interactions": "",
                    "processors": "",
                    "groups": "",
                    "action": "Boost",
                    "isComposite": false,
                    "isPartOfComposite": false
                },
                {
                    "name": "",
                    "id": "20226ba8-ab25-4161-a708-ef93f96f7333",
                    "path": "<Keyboard>/shift",
                    "interactions": "",
                    "processors": "",
                    "groups": "",
                    "action": "Boost",
                    "isComposite": false,
                    "isPartOfComposite": false
                },
                {
                    "name": "",
                    "id": "d39b418b-63a8-40bf-b483-6bcbadeeb1ca",
                    "path": "<Gamepad>/buttonEast",
                    "interactions": "",
                    "processors": "",
                    "groups": "",
                    "action": "Shoot",
                    "isComposite": false,
                    "isPartOfComposite": false
                },
                {
                    "name": "",
                    "id": "e325a2fa-da3c-4126-80a2-60a5abfccf0d",
                    "path": "<Mouse>/leftButton",
                    "interactions": "",
                    "processors": "",
                    "groups": "",
                    "action": "Shoot",
                    "isComposite": false,
                    "isPartOfComposite": false
                },
                {
                    "name": "",
                    "id": "e2fd4241-0268-43e0-bdb7-85543d112aef",
                    "path": "<Gamepad>/buttonNorth",
                    "interactions": "",
                    "processors": "",
                    "groups": "",
                    "action": "Missile",
                    "isComposite": false,
                    "isPartOfComposite": false
                },
                {
                    "name": "",
                    "id": "30269f7c-7f68-4e49-9782-ac06534a7137",
                    "path": "<Mouse>/rightButton",
                    "interactions": "",
                    "processors": "",
                    "groups": "",
                    "action": "Missile",
                    "isComposite": false,
                    "isPartOfComposite": false
                },
                {
                    "name": "",
                    "id": "5398a997-d9f2-4fc8-90ca-f9ad3f7086b5",
                    "path": "<Keyboard>/backslash",
                    "interactions": "",
                    "processors": "",
                    "groups": "",
                    "action": "Save Inputs",
                    "isComposite": false,
                    "isPartOfComposite": false
                }
            ]
        },
        {
            "name": "Menu Controls",
            "id": "a705952d-2613-4a94-b901-a10f33bf81f2",
            "actions": [
                {
                    "name": "ShowForge",
                    "type": "Button",
                    "id": "99512687-2591-436c-835f-ad9804d6cac1",
                    "expectedControlType": "Button",
                    "processors": "",
                    "interactions": ""
                }
            ],
            "bindings": [
                {
                    "name": "",
                    "id": "9dcb2981-d19d-4aad-86e7-618c7f62293a",
                    "path": "<Keyboard>/equals",
                    "interactions": "",
                    "processors": "",
                    "groups": "",
                    "action": "ShowForge",
                    "isComposite": false,
                    "isPartOfComposite": false
                }
            ]
        }
    ],
    "controlSchemes": []
}